sconext_ckan_catalog/__init__.py
sconext_ckan_catalog/ckan_catalog.py
sconext_ckan_catalog-0.0.1b3.dist-info/METADATA
sconext_ckan_catalog-0.0.1b3.dist-info/WHEEL
sconext_ckan_catalog-0.0.1b3.dist-info/entry_points.txt
sconext_ckan_catalog-0.0.1b3.dist-info/top_level.txt
sconext_ckan_catalog-0.0.1b3.dist-info/RECORD
