Metadata-Version: 2.4
Name: sconext-ckan-catalog
Version: 0.0.1b3
Summary: An extension for a CKAN Catalog of the SingularConnector
Home-page: https://www.singularlogic.eu/
Author-email: Iason Sotiropoulos <isotiropoulos@singularlogic.eu>
Classifier: Programming Language :: Python :: 3
Classifier: License :: OSI Approved :: MIT License
Classifier: Operating System :: OS Independent
Requires-Python: >=3.8
Requires-Dist: pydantic>=2.7.0
Requires-Dist: scontoolkit
Dynamic: home-page
